ugad4fun/__init__.py
ugad4fun/recon/__init__.py
ugad4fun/recon/image_recon.py
ugad4fun/recon/line_in_line_out.py
ugad4fun/recon/passthough_demo.py
ugad4fun/recon/plotsave_demo.py
ugad4fun/recon/radial_recon.py
ugad4fun/recon_config/dataflow_monitor.xml
ugad4fun/recon_config/dataflow_monitor_and_plotsave_demo.xml
ugad4fun/recon_config/gadgetron_python_sample.xml
ugad4fun/recon_config/image_recon.xml
ugad4fun/recon_config/line_in_line_out.xml
ugad4fun/recon_config/passthough_demo.xml
ugad4fun/recon_config/plotsave_demo.xml
ugad4fun/recon_config/plotsave_demo_start_by_hand.xml
ugad4fun/recon_config/radial_recon.xml
ugad4fun/tests/__init__.py
ugad4fun/utils/__init__.py
ugad4fun/utils/dummy_conn.py
ugad4fun/version.py
ugad4fun/viz/__init__.py
ugad4fun/viz/plot_one_slice.py
ugad4fun-0.1.0.dist-info/LICENSE
ugad4fun-0.1.0.dist-info/METADATA
ugad4fun-0.1.0.dist-info/WHEEL
ugad4fun-0.1.0.dist-info/RECORD
