Metadata-Version: 2.1
Name: ugad4fun
Version: 0.1.0
Summary: A library providing some MRI reconstruction cases based on Gadgetron.
Home-page: https://github.com/medlab/ugad4fun
License: MIT
Author: ADEPT
Requires-Python: >=3.9,<4.0
Classifier: License :: OSI Approved :: MIT License
Classifier: Programming Language :: Python :: 3
Classifier: Programming Language :: Python :: 3.9
Classifier: Programming Language :: Python :: 3.10
Classifier: Programming Language :: Python :: 3.11
Classifier: Programming Language :: Python :: 3.12
Requires-Dist: ismrmrd (>=1.14.0,<2.0.0)
Requires-Dist: matplotlib (>=3.8.2,<4.0.0)
Requires-Dist: numpy (>=1.26.2,<2.0.0)
Requires-Dist: pynufft (>=2023.2.1,<2024.0.0)
Project-URL: Bug Tracker, https://github.com/medlab/ugad4fun/issues
Project-URL: Repository, https://github.com/medlab/ugad4fun
